{"Objects":[{"Components":[{"Component Tag":"Prototype_Component_Renderer","Level":3},{"Component Tag":"Prototype_Component_Shader_VtxModel","Level":2},{"Component Tag":"Prototype_Component_Transform","Level":3},{"Component Tag":"Prototype_Component_Model_65Boss","Level":2}],"Prototype Object Tag":"Prototype_GameObject_Model_65Boss","Texture Component Count":0},{"Components":[{"Component Tag":"Prototype_Component_Renderer","Level":3},{"Component Tag":"Prototype_Component_Shader_VtxModel","Level":2},{"Component Tag":"Prototype_Component_Transform","Level":3},{"Component Tag":"Prototype_Component_Model_65Boss","Level":2},{"Component Tag":"Prototype_Component_Renderer","Level":3},{"Component Tag":"Prototype_Component_Shader_VtxModel","Level":2},{"Component Tag":"Prototype_Component_Transform","Level":3},{"Component Tag":"Prototype_Component_Model_Snake","Level":2}],"Prototype Object Tag":"Prototype_GameObject_Model_SnakeMap","Texture Component Count":0},{"Components":[{"Component Tag":"Prototype_Component_Renderer","Level":3},{"Component Tag":"Prototype_Component_Shader_VtxModel","Level":2},{"Component Tag":"Prototype_Component_Transform","Level":3},{"Component Tag":"Prototype_Component_Model_65Boss","Level":2},{"Component Tag":"Prototype_Component_Renderer","Level":3},{"Component Tag":"Prototype_Component_Shader_VtxModel","Level":2},{"Component Tag":"Prototype_Component_Transform","Level":3},{"Component Tag":"Prototype_Component_Model_Snake","Level":2},{"Component Tag":"Prototype_Component_Renderer","Level":3},{"Component Tag":"Prototype_Component_Shader_VtxModel","Level":2},{"Component Tag":"Prototype_Component_Transform","Level":3},{"Component Tag":"Prototype_Component_Model_Test","Level":2}],"Prototype Object Tag":"Prototype_GameObject_Test","Texture Component Count":0}]}